Pokeam_Base/__init__.py
Pokeam_Base/pokemon.csv
Pokeam_Base/random_pokemon.py
Pokeam_Base-1.0.2.dist-info/METADATA
Pokeam_Base-1.0.2.dist-info/WHEEL
Pokeam_Base-1.0.2.dist-info/top_level.txt
Pokeam_Base-1.0.2.dist-info/RECORD
